Metadata-Version: 1.1
Name: fan-duel
Version: 0.1
Summary: A FanDuel client
Home-page: https://github.com/jaebradley/fan_duel_client
Author: Jae Bradley
Author-email: jae.b.bradley@gmail.com
License: UNKNOWN
Download-URL: https://github.com/jaebradley/fan_duel_client/tarball/0.1
Keywords: sports,dfs,fanduel
Platform: UNKNOWN
